tracenest/__init__.py
tracenest/logger.py
tracenest/core/__init__.py
tracenest/core/config.py
tracenest/core/formatter.py
tracenest/core/retention.py
tracenest/core/rotation.py
tracenest/core/writer.py
tracenest/fastapi/__init__.py
tracenest/fastapi/middleware.py
tracenest/ui/__init__.py
tracenest/ui/router.py
tracenest/ui/templates/app.js
tracenest/ui/templates/index.html
tracenest/ui/templates/styles.css
tracenest/utils/__init__.py
tracenest/utils/filesystem.py
tracenest/utils/time.py
tracenest-0.1.1.dist-info/licenses/LICENSE
tracenest-0.1.1.dist-info/METADATA
tracenest-0.1.1.dist-info/WHEEL
tracenest-0.1.1.dist-info/top_level.txt
tracenest-0.1.1.dist-info/RECORD
