Metadata-Version: 2.4
Name: tracenest
Version: 0.1.1
Summary: Developer-first, local-first logging infrastructure for Python applications
Author-email: VishwajitVM <vishwajitmall50@gmail.com>
License: MIT License
Project-URL: Homepage, https://github.com/vishwajitvm/tracenest
Project-URL: Repository, https://github.com/vishwajitvm/tracenest
Project-URL: Issues, https://github.com/vishwajitvm/tracenest/issues
Keywords: logging,observability,logs,fastapi,developer-tools,local-first,infrastructure
Classifier: Development Status :: 3 - Alpha
Classifier: Intended Audience :: Developers
Classifier: Topic :: System :: Logging
Classifier: License :: OSI Approved :: MIT License
Classifier: Programming Language :: Python :: 3
Classifier: Programming Language :: Python :: 3 :: Only
Classifier: Programming Language :: Python :: 3.9
Classifier: Programming Language :: Python :: 3.10
Classifier: Programming Language :: Python :: 3.11
Classifier: Programming Language :: Python :: 3.12
Classifier: Operating System :: OS Independent
Requires-Python: >=3.9
License-File: LICENSE
Provides-Extra: fastapi
Requires-Dist: fastapi>=0.100.0; extra == "fastapi"
Provides-Extra: dev
Requires-Dist: pytest>=7.0; extra == "dev"
Requires-Dist: pytest-cov; extra == "dev"
Requires-Dist: ruff; extra == "dev"
Requires-Dist: black; extra == "dev"
Requires-Dist: mypy; extra == "dev"
Requires-Dist: uvicorn[standard]; extra == "dev"
Provides-Extra: docs
Requires-Dist: mkdocs; extra == "docs"
Requires-Dist: mkdocs-material; extra == "docs"
Dynamic: license-file
